likefit.py
likefit-0.2.2.dist-info/LICENSE
likefit-0.2.2.dist-info/METADATA
likefit-0.2.2.dist-info/WHEEL
likefit-0.2.2.dist-info/top_level.txt
likefit-0.2.2.dist-info/RECORD
