Metadata-Version: 2.1
Name: likefit
Version: 0.2.2
Summary: Fit data with least squares and other likelihood methods
Author-email: Diego Ravignani <diego.ravignani@gmail.com>
License: MIT License
Project-URL: Homepage, https://github.com/ravignad/likefit
Keywords: fit,likelihood,scipy
Classifier: License :: OSI Approved :: MIT License
Classifier: Programming Language :: Python
Classifier: Programming Language :: Python :: 3
Requires-Python: >=3.8
License-File: LICENSE
Requires-Dist: scipy >=1.9.3
Requires-Dist: matplotlib >=3.7.4
Provides-Extra: dev
Requires-Dist: pip-tools ; extra == 'dev'
Requires-Dist: pandas ; extra == 'dev'
Requires-Dist: pytest ; extra == 'dev'
